pyritex/__init__.py
pyritex/log.py
pyritex/netlink/__init__.py
pyritex/netlink/consts.py
pyritex/netlink/message.py
pyritex/netlink/parsing.py
pyritex/netlink/socket.py
pyritex/netlink/rtnl/consts.py
pyritex-tools/build-api.py
pyritex-0.1.0.dist-info/METADATA
pyritex-0.1.0.dist-info/WHEEL
pyritex-0.1.0.dist-info/top_level.txt
pyritex-0.1.0.dist-info/RECORD
